PyKDL.cpython-36m-x86_64-linux-gnu.so
PyKDL-1.4.0.dist-info/DESCRIPTION.rst
PyKDL-1.4.0.dist-info/METADATA
PyKDL-1.4.0.dist-info/RECORD
PyKDL-1.4.0.dist-info/WHEEL
PyKDL-1.4.0.dist-info/metadata.json
PyKDL-1.4.0.dist-info/top_level.txt
