Metadata-Version: 2.0
Name: PyKDL
Version: 1.4.0
Summary: Python binding for KDL
Home-page: https://github.com/orocos/orocos_kinematics_dynamics
Author: Ruben Smits
Author-email: ruben@intermodalics.eu
License: LGPL
Platform: UNKNOWN
Requires-Dist: sip
